{
  "nodes": [
    {
      "id": "src_components_homeclient_tsx",
      "label": "HomeClient.tsx",
      "file_type": "code",
      "source_file": "src\\components\\HomeClient.tsx",
      "source_location": "L1"
    },
    {
      "id": "components_homeclient_homeclient",
      "label": "HomeClient()",
      "file_type": "code",
      "source_file": "src\\components\\HomeClient.tsx",
      "source_location": "L19"
    },
    {
      "id": "components_homeclient_dashboardstats",
      "label": "DashboardStats()",
      "file_type": "code",
      "source_file": "src\\components\\HomeClient.tsx",
      "source_location": "L82"
    }
  ],
  "edges": [
    {
      "source": "src_components_homeclient_tsx",
      "target": "react",
      "relation": "imports_from",
      "confidence": "EXTRACTED",
      "source_file": "src\\components\\HomeClient.tsx",
      "source_location": "L3",
      "weight": 1.0
    },
    {
      "source": "src_components_homeclient_tsx",
      "target": "link",
      "relation": "imports_from",
      "confidence": "EXTRACTED",
      "source_file": "src\\components\\HomeClient.tsx",
      "source_location": "L9",
      "weight": 1.0
    },
    {
      "source": "src_components_homeclient_tsx",
      "target": "i_promptamist_src_components_ui_button",
      "relation": "imports_from",
      "confidence": "EXTRACTED",
      "source_file": "src\\components\\HomeClient.tsx",
      "source_location": "L10",
      "weight": 1.0
    },
    {
      "source": "src_components_homeclient_tsx",
      "target": "i_promptamist_src_components_ui_card",
      "relation": "imports_from",
      "confidence": "EXTRACTED",
      "source_file": "src\\components\\HomeClient.tsx",
      "source_location": "L11",
      "weight": 1.0
    },
    {
      "source": "src_components_homeclient_tsx",
      "target": "i_promptamist_src_components_ui_skeleton",
      "relation": "imports_from",
      "confidence": "EXTRACTED",
      "source_file": "src\\components\\HomeClient.tsx",
      "source_location": "L12",
      "weight": 1.0
    },
    {
      "source": "src_components_homeclient_tsx",
      "target": "convex_generated_api",
      "relation": "imports_from",
      "confidence": "EXTRACTED",
      "source_file": "src\\components\\HomeClient.tsx",
      "source_location": "L13",
      "weight": 1.0
    },
    {
      "source": "src_components_homeclient_tsx",
      "target": "react",
      "relation": "imports_from",
      "confidence": "EXTRACTED",
      "source_file": "src\\components\\HomeClient.tsx",
      "source_location": "L14",
      "weight": 1.0
    },
    {
      "source": "src_components_homeclient_tsx",
      "target": "i_promptamist_src_lib_utils",
      "relation": "imports_from",
      "confidence": "EXTRACTED",
      "source_file": "src\\components\\HomeClient.tsx",
      "source_location": "L15",
      "weight": 1.0
    },
    {
      "source": "src_components_homeclient_tsx",
      "target": "react",
      "relation": "imports_from",
      "confidence": "EXTRACTED",
      "source_file": "src\\components\\HomeClient.tsx",
      "source_location": "L17",
      "weight": 1.0
    },
    {
      "source": "src_components_homeclient_tsx",
      "target": "components_homeclient_homeclient",
      "relation": "contains",
      "confidence": "EXTRACTED",
      "source_file": "src\\components\\HomeClient.tsx",
      "source_location": "L19",
      "weight": 1.0
    },
    {
      "source": "src_components_homeclient_tsx",
      "target": "components_homeclient_dashboardstats",
      "relation": "contains",
      "confidence": "EXTRACTED",
      "source_file": "src\\components\\HomeClient.tsx",
      "source_location": "L82",
      "weight": 1.0
    }
  ],
  "raw_calls": [
    {
      "caller_nid": "components_homeclient_dashboardstats",
      "callee": "useState",
      "is_member_call": false,
      "source_file": "src\\components\\HomeClient.tsx",
      "source_location": "L83"
    },
    {
      "caller_nid": "components_homeclient_dashboardstats",
      "callee": "useQuery",
      "is_member_call": false,
      "source_file": "src\\components\\HomeClient.tsx",
      "source_location": "L84"
    },
    {
      "caller_nid": "components_homeclient_dashboardstats",
      "callee": "formatRelativeTime",
      "is_member_call": false,
      "source_file": "src\\components\\HomeClient.tsx",
      "source_location": "L174"
    }
  ]
}
